setup.py
pytest_bench/__init__.py
pytest_bench/_version.py
pytest_bench/plugin.py
pytest_bench/terminal.py
pytest_bench.egg-info/PKG-INFO
pytest_bench.egg-info/SOURCES.txt
pytest_bench.egg-info/dependency_links.txt
pytest_bench.egg-info/entry_points.txt
pytest_bench.egg-info/requires.txt
pytest_bench.egg-info/top_level.txt